{
  "2254" : {
    "2255|2-2254|2" : [
      2765,
      726
    ]
  },
  "2253" : {
    "2255|2-2253|2" : [
      2754,
      726
    ]
  },
  "2495" : {
    "177|1-2495|2" : [
      3260,
      775
    ]
  },
  "2493" : {
    "177|1-2493|2" : [
      3249,
      775
    ]
  },
  "2492" : {
    "177|1-2492|2" : [
      3238,
      775
    ]
  },
  "2491" : {
    "177|1-2491|2" : [
      3227,
      775
    ]
  },
  "2490" : {
    "177|1-2490|2" : [
      3216,
      775
    ]
  },
  "2504" : {
    "177|1-2504|2" : [
      3348,
      775
    ]
  },
  "2526" : {
    "177|1-2526|2" : [
      3546,
      775
    ]
  },
  "2503" : {
    "177|1-2503|2" : [
      3337,
      775
    ]
  },
  "2524" : {
    "177|1-2524|2" : [
      3524,
      775
    ]
  },
  "minimal" : {
    "minimal" : [
      3106,
      808
    ]
  },
  "2501" : {
    "177|1-2501|2" : [
      3315,
      775
    ]
  },
  "2489" : {
    "177|1-2489|2" : [
      3205,
      775
    ]
  },
  "2500" : {
    "177|1-2500|2" : [
      3304,
      775
    ]
  },
  "2522" : {
    "177|1-2522|2" : [
      3502,
      775
    ]
  },
  "2488" : {
    "177|1-2488|2" : [
      3194,
      775
    ]
  },
  "2487" : {
    "177|1-2487|2" : [
      3183,
      775
    ]
  },
  "2509" : {
    "177|1-2509|2" : [
      3403,
      775
    ]
  },
  "2508" : {
    "177|1-2508|2" : [
      3392,
      775
    ]
  },
  "2507" : {
    "177|1-2507|2" : [
      3381,
      775
    ]
  },
  "2506" : {
    "177|1-2506|2" : [
      3370,
      775
    ]
  },
  "2505" : {
    "177|1-2505|2" : [
      3359,
      775
    ]
  },
  "2485" : {
    "177|1-2485|2" : [
      3161,
      775
    ]
  },
  "2482" : {
    "177|1-2482|2" : [
      3139,
      775
    ]
  },
  "2512" : {
    "177|1-2512|2" : [
      3436,
      775
    ]
  },
  "2478" : {
    "177|1-2478|8" : [
      3106,
      808
    ]
  },
  "2511" : {
    "177|1-2511|2" : [
      3425,
      775
    ]
  },
  "2499" : {
    "177|1-2499|2" : [
      3293,
      775
    ]
  },
  "2510" : {
    "177|1-2510|2" : [
      3414,
      775
    ]
  },
  "2498" : {
    "177|1-2498|2" : [
      3282,
      775
    ]
  },
  "2497" : {
    "177|1-2497|2" : [
      3271,
      775
    ]
  },
  "2519" : {
    "177|1-2519|2" : [
      3480,
      775
    ]
  },
  "2517" : {
    "177|1-2517|2" : [
      3458,
      775
    ]
  }
}