{
  "" : {
    "" : [
      0,
      1
    ]
  },
  "2052" : {
    "1131|6-1137|11.a-2052|5" : [
      1034,
      768
    ],
    "1132|2-1137|10-2052|5" : [
      1034,
      715
    ]
  },
  "1657" : {
    "1132|2-1124|22-1657|3" : [
      263,
      382
    ],
    "1131|6-1657|4" : [
      263,
      435
    ],
    "1657|6" : [
      263,
      493
    ]
  },
  "1612" : {
    "1131|6-1612|4" : [
      165,
      435
    ],
    "1132|2-1124|22-1612|3" : [
      165,
      382
    ],
    "1127|5.b-1612|5" : [
      165,
      505
    ],
    "1127|6-1612|5" : [
      165,
      549
    ]
  },
  "2105" : {
    "166|3-2105|3.b" : [
      1541,
      561
    ]
  },
  "1750" : {
    "1131|6-1750|4" : [
      242,
      435
    ],
    "1132|2-1124|22-1750|3" : [
      242,
      382
    ]
  },
  "2102" : {
    "166|3-2102|3.b" : [
      1507,
      544
    ]
  },
  "1639" : {
    "1132|2-1124|22-1639|7" : [
      219,
      698
    ]
  },
  "1738" : {
    "1127|6-1738|16" : [
      117,
      518
    ],
    "1130|3.b-1738|18" : [
      117,
      568
    ],
    "1131|6-1137|11.a-1738|14.b" : [
      117,
      465
    ],
    "1132|2-1137|10-1738|14.b" : [
      117,
      412
    ]
  },
  "1736" : {
    "1130|3.b-1736|18" : [
      96,
      559
    ],
    "1127|6-1736|16" : [
      96,
      509
    ],
    "1131|6-1137|11.a-1736|14.b" : [
      96,
      456
    ],
    "1132|2-1137|10-1736|14.b" : [
      96,
      403
    ]
  },
  "2082" : {
    "1132|2-1124|22-2083|28-2082|3" : [
      1338,
      577
    ],
    "1127|5.b-2083|32.a-2082|3" : [
      1338,
      703
    ],
    "1127|6-2083|32.a-2082|3" : [
      1338,
      747
    ],
    "1131|6-2083|29-2082|3" : [
      1338,
      630
    ]
  },
  "1624" : {
    "1131|6-1624|6" : [
      50,
      383
    ],
    "1132|2-1124|22-1624|5" : [
      50,
      330
    ]
  },
  "1645" : {
    "1132|2-1124|22-1645|5" : [
      290,
      751
    ],
    "1131|6-1645|7" : [
      290,
      807
    ],
    "1130|3.b-1645|8" : [
      290,
      856
    ]
  },
  "1644" : {
    "1132|2-1124|22-1644|5" : [
      317,
      751
    ],
    "1131|6-1644|7" : [
      317,
      807
    ],
    "1130|3.b-1644|10" : [
      317,
      913
    ],
    "1644|9" : [
      317,
      865
    ]
  },
  "1643" : {
    "1132|2-1124|22-1643|5" : [
      252,
      751
    ],
    "1131|6-1643|7" : [
      252,
      807
    ],
    "1130|3.b-1643|10" : [
      252,
      913
    ],
    "1643|9" : [
      252,
      865
    ]
  },
  "1642" : {
    "1642|9.b" : [
      286,
      858
    ],
    "1131|6-1642|7" : [
      286,
      812
    ],
    "1132|2-1124|22-1642|5" : [
      286,
      754
    ]
  },
  "1641" : {
    "1641|10.b" : [
      268,
      855
    ],
    "1131|6-1641|8" : [
      268,
      810
    ],
    "1132|2-1124|22-1641|6" : [
      268,
      752
    ]
  },
  "2235" : {
    "1148|8-2235|4" : [
      2561,
      575
    ]
  },
  "1640" : {
    "1131|6-1640|2" : [
      219,
      758
    ],
    "1130|3.b-1640|3" : [
      219,
      807
    ]
  },
  "1761" : {
    "1132|2-1124|22-1761|6" : [
      131,
      331
    ],
    "1131|6-1761|7" : [
      131,
      384
    ]
  },
  "1728" : {
    "1155|8-1133|22.a.i-1728|2" : [
      227,
      964
    ],
    "1155|7-1133|22.a.i-1728|2" : [
      227,
      922
    ],
    "1155|4-1133|22.a.i-1728|2" : [
      227,
      875
    ]
  },
  "1727" : {
    "1132|2-1124|22-1727|5" : [
      227,
      679
    ]
  },
  "1726" : {
    "1132|2-1124|22-1726|2.e" : [
      167,
      687
    ]
  },
  "1647" : {
    "1132|2-1124|22-1647|3" : [
      193,
      382
    ],
    "1131|6-1647|4" : [
      193,
      435
    ],
    "1647|6" : [
      193,
      493
    ]
  }
}