{
  "2254" : {
    "2254|1" : [
      2765,
      747
    ]
  },
  "2077" : {
    "2077|1" : [
      1288,
      1980
    ]
  },
  "2253" : {
    "2253|1" : [
      2754,
      747
    ]
  },
  "2252" : {
    "2252|1" : [
      2744,
      764
    ]
  },
  "2273" : {
    "2271|1-2273|2" : [
      2919,
      749
    ]
  },
  "2052" : {
    "2052|1" : [
      1034,
      700
    ]
  },
  "2272" : {
    "2271|1-2272|2" : [
      2908,
      749
    ]
  },
  "2270" : {
    "2271|1-2270|2" : [
      2897,
      749
    ]
  },
  "2248" : {
    "2248|1" : [
      2699,
      747
    ]
  },
  "2588" : {
    "193|1-2588|1" : [
      3965,
      701
    ]
  },
  "2246" : {
    "2246|1" : [
      2677,
      747
    ]
  },
  "2245" : {
    "2245|1" : [
      2666,
      747
    ]
  },
  "2068" : {
    "2068|1" : [
      1199,
      700
    ]
  },
  "2244" : {
    "2244|1" : [
      2655,
      747
    ]
  },
  "2266" : {
    "2266|1" : [
      2853,
      747
    ]
  },
  "2243" : {
    "2243|1" : [
      2644,
      747
    ]
  },
  "2265" : {
    "2265|1" : [
      2842,
      747
    ]
  },
  "2264" : {
    "2264|1" : [
      2831,
      747
    ]
  },
  "2241" : {
    "2241|1" : [
      2622,
      747
    ]
  },
  "2263" : {
    "2263|1" : [
      2820,
      747
    ]
  },
  "2240" : {
    "2240|1" : [
      2611,
      747
    ]
  },
  "2261" : {
    "2261|1" : [
      2798,
      747
    ]
  },
  "2239" : {
    "2239|1" : [
      2600,
      747
    ]
  },
  "2259" : {
    "2259|1" : [
      2787,
      747
    ]
  },
  "2258" : {
    "2258|1" : [
      2776,
      747
    ]
  },
  "2059" : {
    "193|1-2059|1" : [
      1100,
      701
    ]
  },
  "2277" : {
    "2277|1" : [
      2941,
      970
    ]
  }
}