{
  "2056" : {
    "18400-18390" : [
      1077,
      1
    ]
  },
  "2044" : {
    "18057" : [
      967,
      1
    ]
  },
  "2055" : {
    "18400-18376" : [
      1066,
      1
    ]
  },
  "2054" : {
    "18340" : [
      1055,
      1
    ]
  },
  "2065" : {
    "18539" : [
      1165,
      1
    ]
  },
  "2053" : {
    "18313" : [
      1044,
      1
    ]
  },
  "2060" : {
    "18470" : [
      1110,
      1
    ]
  },
  "1502" : {
    "1957-2025-2622-13358-13289" : [
      720,
      1
    ]
  },
  "2238" : {
    "22458" : [
      2589,
      1
    ],
    "22469" : [
      2590,
      1
    ]
  },
  "883" : {
    "1957-2025-2650-4714" : [
      140,
      1
    ]
  },
  "2105" : {
    "1957-2025-2650-19492" : [
      1538,
      1
    ]
  },
  "1499" : {
    "1957-2025-2650-13358-13255" : [
      192,
      1
    ]
  },
  "2049" : {
    "18231" : [
      1011,
      1
    ]
  },
  "2478" : {
    "1957-2025-25528" : [
      3105,
      1
    ]
  },
  "2058" : {
    "18425" : [
      1088,
      1
    ]
  },
  "2069" : {
    "18642" : [
      1209,
      1
    ]
  }
}