{
  "" : {
    "" : [
      0,
      1
    ]
  },
  "1462" : {
    "1477|3.b-1462|4" : [
      138,
      323
    ]
  },
  "1459" : {
    "1459|2.a" : [
      162,
      312
    ]
  },
  "1535" : {
    "1535|3" : [
      13,
      319
    ]
  },
  "1534" : {
    "1534|1" : [
      145,
      398
    ]
  },
  "1533" : {
    "1533|1" : [
      111,
      402
    ]
  },
  "1499" : {
    "1504|3-1499|1" : [
      192,
      709
    ]
  },
  "1554" : {
    "1554|1" : [
      287,
      324
    ],
    "1554|4" : [
      287,
      334
    ]
  },
  "1476" : {
    "1476|12" : [
      237,
      478
    ],
    "1476|7" : [
      237,
      381
    ]
  },
  "1498" : {
    "1504|3-1498|1" : [
      144,
      391
    ]
  },
  "1553" : {
    "1553|1" : [
      169,
      318
    ],
    "1553|2" : [
      169,
      326
    ]
  },
  "1453" : {
    "1453|4.a" : [
      363,
      1190
    ]
  },
  "1475" : {
    "1475|12" : [
      220,
      478
    ],
    "1475|7" : [
      220,
      381
    ]
  },
  "1497" : {
    "1504|3-1497|1" : [
      202,
      355
    ]
  },
  "1552" : {
    "1552|1" : [
      158,
      318
    ]
  },
  "1430" : {
    "1430|2" : [
      4,
      335
    ]
  },
  "1452" : {
    "1452|3.a" : [
      544,
      1202
    ]
  },
  "1496" : {
    "1504|3-1496|1" : [
      194,
      709
    ]
  },
  "1738" : {
    "1738|31.b.ii" : [
      227,
      1129
    ],
    "1738|25.b.i" : [
      227,
      747
    ],
    "1738|25.a.i" : [
      132,
      661
    ],
    "1738|31.a.i" : [
      228,
      747
    ],
    "1111|6-172|3-1738|31.b.ii" : [
      227,
      1118
    ]
  },
  "1473" : {
    "1473|7" : [
      236,
      408
    ]
  },
  "1495" : {
    "1504|3-1495|1" : [
      143,
      391
    ]
  },
  "1503" : {
    "1504|3-1503|1" : [
      725,
      1183
    ]
  },
  "1502" : {
    "1504|3-1502|1" : [
      720,
      1190
    ]
  },
  "1524" : {
    "1524|15.a" : [
      832,
      1367
    ],
    "1524|11" : [
      832,
      1355
    ],
    "1524|5.b.i" : [
      832,
      1337
    ]
  },
  "1501" : {
    "1504|3-1501|1" : [
      642,
      1170
    ]
  },
  "1523" : {
    "1523|5.b.i" : [
      819,
      1331
    ],
    "1523|11" : [
      819,
      1347
    ]
  },
  "1500" : {
    "1504|3-1500|1" : [
      191,
      355
    ]
  },
  "1522" : {
    "1522|9.a.ii.1" : [
      816,
      1336
    ]
  },
  "1742" : {
    "1742|8.c" : [
      239,
      414
    ]
  },
  "1521" : {
    "1521|11" : [
      722,
      1246
    ]
  },
  "1520" : {
    "1520|4.b.i" : [
      704,
      1297
    ]
  },
  "1740" : {
    "1740|8.c" : [
      208,
      411
    ]
  },
  "1429" : {
    "1429|5" : [
      9,
      317
    ]
  },
  "1526" : {
    "1526|7" : [
      501,
      1204
    ]
  }
}