{
  "1451" : {
    "95|4.c-1451|2" : [
      262,
      1122
    ]
  },
  "1495" : {
    "95|4.c-1504|5-1495|1" : [
      505,
      1137
    ]
  },
  "1472" : {
    "95|4.c-1477|3.a.ii-1472|4" : [
      678,
      1171
    ]
  },
  "1471" : {
    "95|4.c-1477|3.a.ii-1471|4" : [
      620,
      1171
    ]
  },
  "1502" : {
    "95|4.c-1504|5-1502|1" : [
      720,
      1157
    ]
  },
  "1524" : {
    "95|4.c-1525|3-1524|5.a.i" : [
      832,
      1259
    ]
  },
  "1501" : {
    "95|4.c-1504|5-1501|1" : [
      642,
      1137
    ]
  },
  "1523" : {
    "95|4.c-1525|3-1523|5.a.i" : [
      819,
      1253
    ]
  },
  "minimal" : {
    "minimal" : [
      220,
      360
    ]
  },
  "1522" : {
    "95|4.c-1525|3-1522|9.a.i.1" : [
      816,
      1258
    ]
  },
  "1499" : {
    "95|4.c-1504|5-1499|1" : [
      616,
      1157
    ]
  },
  "1476" : {
    "95|4.c-1477|3.a.ii-1476|12" : [
      237,
      416
    ],
    "1478|1.e.ii-1477|2-1476|12" : [
      237,
      360
    ]
  },
  "1498" : {
    "95|4.c-1504|5-1498|1" : [
      488,
      1137
    ]
  },
  "1520" : {
    "95|4.c-1525|3-1520|4.a.i" : [
      704,
      1219
    ]
  },
  "1453" : {
    "95|4.c-1453|2" : [
      363,
      1126
    ]
  },
  "1475" : {
    "95|4.c-1477|3.a.ii-1475|12" : [
      220,
      416
    ],
    "1478|1.e.ii-1477|2-1475|12" : [
      220,
      360
    ]
  },
  "1452" : {
    "95|4.c-1452|2" : [
      544,
      1138
    ]
  },
  "1496" : {
    "95|4.c-1504|5-1496|1" : [
      592,
      1157
    ]
  },
  "1549" : {
    "95|4.c-1549|2" : [
      325,
      1122
    ]
  },
  "1526" : {
    "95|4.c-1526|2" : [
      501,
      1129
    ]
  }
}