{
  "" : {
    "" : [
      40,
      1
    ]
  },
  "1440" : {
    "1100|1-163|1-1021|4-1036|4-96|4.c-1440|5" : [
      99,
      864
    ]
  },
  "1384" : {
    "1100|1-96|3.c-1384|1.d" : [
      1288,
      1854
    ]
  },
  "2483" : {
    "1100|1-163|1-2483|6" : [
      3150,
      1090
    ]
  },
  "2480" : {
    "1100|1-163|1-2480|8" : [
      3127,
      710
    ]
  },
  "2524" : {
    "1100|1-163|1-2524|4.e.i" : [
      3525,
      827
    ],
    "1100|1-163|1-2524|5" : [
      3524,
      793
    ]
  },
  "1246" : {
    "1100|1-163|1-1246|2" : [
      36,
      322
    ]
  },
  "2478" : {
    "1100|1-163|1-2478|13" : [
      3106,
      892
    ]
  },
  "2511" : {
    "1100|1-163|1-2511|15" : [
      3425,
      886
    ]
  },
  "2477" : {
    "1100|1-163|1-2477|5.e" : [
      3101,
      565
    ]
  },
  "2510" : {
    "1100|1-163|1-2510|3.a" : [
      3414,
      792
    ]
  },
  "2506" : {
    "1100|1-163|1-2506|5.a" : [
      3371,
      823
    ],
    "1100|1-163|1-2506|6" : [
      3370,
      794
    ]
  },
  "2517" : {
    "1100|1-163|1-2517|15" : [
      3458,
      885
    ],
    "1100|1-163|1-2517|19.a" : [
      3461,
      1160
    ],
    "1100|1-163|1-2517|20" : [
      3458,
      1086
    ]
  },
  "2505" : {
    "1100|1-163|1-2505|3.a" : [
      3359,
      792
    ]
  }
}