{
  "minimal" : {
    "minimal" : [
      1166,
      660
    ]
  },
  "1511" : {
    "1511|5.a.i" : [
      505,
      1370
    ]
  },
  "2049" : {
    "182|1-2049|2" : [
      1012,
      660
    ]
  },
  "2069" : {
    "182|1-2069|2" : [
      1210,
      660
    ]
  },
  "2056" : {
    "2057|2-2056|1" : [
      1078,
      660
    ]
  },
  "2044" : {
    "2044|3.a.ii" : [
      969,
      683
    ]
  },
  "2055" : {
    "2057|2-2055|1" : [
      1067,
      660
    ]
  },
  "2054" : {
    "2054|2" : [
      1056,
      659
    ]
  },
  "2065" : {
    "182|1-2065|2" : [
      1166,
      660
    ]
  }
}