{
  "1645" : {
    "1645|6" : [
      290,
      761
    ]
  },
  "1644" : {
    "1644|6" : [
      317,
      761
    ]
  },
  "minimal" : {
    "minimal" : [
      167,
      697
    ]
  },
  "1643" : {
    "1643|6" : [
      252,
      761
    ]
  },
  "1642" : {
    "1642|6" : [
      286,
      764
    ]
  },
  "1641" : {
    "1641|7" : [
      268,
      762
    ]
  },
  "1639" : {
    "1639|8" : [
      219,
      708
    ]
  },
  "1727" : {
    "1727|6" : [
      227,
      689
    ]
  },
  "1726" : {
    "1726|2.f" : [
      167,
      697
    ]
  }
}